.gitignore
.gitmodules
README
setup.cfg
setup.py
Flask_Zen.egg-info/PKG-INFO
Flask_Zen.egg-info/SOURCES.txt
Flask_Zen.egg-info/dependency_links.txt
Flask_Zen.egg-info/not-zip-safe
Flask_Zen.egg-info/requires.txt
Flask_Zen.egg-info/top_level.txt
docs/Makefile
docs/_themes
docs/conf.py
docs/index.rst
docs/make.bat
docs/_static/README
docs/_static/logo.png
docs/_static/logo.pxm
flaskext/__init__.py
flaskext/zen.py