Metadata-Version: 1.0
Name: Flask-Zen
Version: 0.2
Summary: Flask-Script commands to integrate with PyZen.
Home-page: http://github.com/coderanger/flask-zen
Author: Noah Kantrowitz
Author-email: noah@coderanger.net
License: BSD
Keywords: test unittest continuous flask
Platform: UNKNOWN
Classifier: Development Status :: 3 - Alpha
Classifier: Environment :: Console
Classifier: Environment :: Win32 (MS Windows)
Classifier: License :: OSI Approved :: BSD License
Classifier: Natural Language :: English
Classifier: Operating System :: OS Independent
Classifier: Programming Language :: Python
